tumblrbot/__init__.py
tumblrbot/__main__.py
tumblrbot/flow/__init__.py
tumblrbot/flow/download.py
tumblrbot/flow/examples.py
tumblrbot/flow/fine_tune.py
tumblrbot/flow/generate.py
tumblrbot/utils/__init__.py
tumblrbot/utils/common.py
tumblrbot/utils/models.py
tumblrbot/utils/tumblr.py
tumblrbot-1.9.6.dist-info/entry_points.txt
tumblrbot-1.9.6.dist-info/WHEEL
tumblrbot-1.9.6.dist-info/METADATA
tumblrbot-1.9.6.dist-info/RECORD
