Metadata-Version: 2.4
Name: tumblrbot
Version: 1.9.6
Summary: An updated bot that posts to Tumblr, based on your very own blog!
Requires-Python: >= 3.14
Requires-Dist: openai
Requires-Dist: pydantic
Requires-Dist: requests
Requires-Dist: requests-oauthlib
Requires-Dist: rich
Requires-Dist: tenacity
Requires-Dist: tiktoken
Requires-Dist: tomlkit
Project-URL: Funding, https://ko-fi.com/maidscientistizutsumimarin
Project-URL: Source, https://github.com/MaidScientistIzutsumiMarin/tumblrbot
